[
{"Image Link": "https://images.brickset.com/sets/small/10264-1.jpg?201812030159"},
{"Image Link": "https://images.brickset.com/sets/small/10265-1.jpg?201902220155"},
{"Image Link": "https://images.brickset.com/sets/small/10266-1.jpg?201905300158"},
{"Image Link": "https://images.brickset.com/sets/small/10267-1.jpg?201909120259"},
{"Image Link": "https://images.brickset.com/sets/small/10269-1.jpg?201907090157"},
{"Image Link": "https://images.brickset.com/sets/small/10766-1.jpg?201904230852"},
{"Image Link": "https://images.brickset.com/sets/small/10767-1.jpg?201904230852"},
{"Image Link": "https://images.brickset.com/sets/small/10768-1.jpg?201904230852"},
{"Image Link": "https://images.brickset.com/sets/small/10769-1.jpg?201904230852"},
{"Image Link": "https://images.brickset.com/sets/small/10770-1.jpg?201904230852"},
{"Image Link": "https://images.brickset.com/sets/small/10771-1.jpg?201904230852"},
{"Image Link": "https://images.brickset.com/sets/small/10883-1.jpg?201812041022"},
{"Image Link": "https://images.brickset.com/sets/small/10884-1.jpg?201812041022"},
{"Image Link": "https://images.brickset.com/sets/small/10885-1.jpg?201812041022"},
{"Image Link": "https://images.brickset.com/sets/small/10886-1.jpg?201812041022"},
{"Image Link": "https://images.brickset.com/sets/small/10887-1.jpg?201901050928"},
{"Image Link": "https://images.brickset.com/sets/small/10889-1.jpg?201905140825"},
{"Image Link": "https://images.brickset.com/sets/small/10893-1.jpg?201812120846"},
{"Image Link": "https://images.brickset.com/sets/small/10894-1.jpg?201902200914"},
{"Image Link": "https://images.brickset.com/sets/small/10895-1.jpg?201811200639"},
{"Image Link": "https://images.brickset.com/sets/small/10897-1.jpg?201812120846"},
{"Image Link": "https://images.brickset.com/sets/small/10898-1.jpg?201812120846"},
{"Image Link": "https://images.brickset.com/sets/small/10899-1.jpg?201907130955"},
{"Image Link": "https://images.brickset.com/sets/small/10900-1.jpg?201812041022"},
{"Image Link": "https://images.brickset.com/sets/small/10901-1.jpg?201812041022"},
{"Image Link": "/assets/images/misc/rlfm-white-logo.png"},
{"Image Link": "https://images.brickset.com/sets/small/10902-1.jpg?201812041022"},
{"Image Link": "https://images.brickset.com/sets/small/10903-1.jpg?201812041022"},
{"Image Link": "https://images.brickset.com/sets/small/10904-1.jpg?201905140825"},
{"Image Link": "https://images.brickset.com/sets/small/10906-1.jpg?201905140825"},
{"Image Link": "https://images.brickset.com/sets/small/10907-1.jpg?201905140825"},
{"Image Link": "https://images.brickset.com/sets/small/10908-1.jpg?201812041022"},
{"Image Link": "https://images.brickset.com/sets/small/10910-1.jpg?201905140825"},
{"Image Link": "https://images.brickset.com/sets/small/11001-1.jpg?201812041022"},
{"Image Link": "https://images.brickset.com/sets/small/11002-1.jpg?201812041022"},
{"Image Link": "https://images.brickset.com/sets/small/11003-1.jpg?201812041022"},
{"Image Link": "https://images.brickset.com/sets/small/11004-1.jpg?201905140825"},
{"Image Link": "https://images.brickset.com/sets/small/11005-1.jpg?201901050928"},
{"Image Link": "https://images.brickset.com/sets/small/11920-1.jpg?201908180915"},
{"Image Link": "https://images.brickset.com/sets/small/11922-1.jpg?202012120946"},
{"Image Link": "https://images.brickset.com/sets/small/11923-1.jpg?202006220843"},
{"Image Link": "/assets/images/misc/blankbox.gif"},
{"Image Link": "https://images.brickset.com/sets/small/11926-1.jpg?201911010429"},
{"Image Link": "https://images.brickset.com/sets/small/21043-1.jpg?201812120846"},
{"Image Link": "https://images.brickset.com/sets/small/21044-1.jpg?201812120846"},
{"Image Link": "https://images.brickset.com/sets/small/21045-1.jpg?201904270648"},
{"Image Link": "https://images.brickset.com/sets/small/21046-1.jpg?201905140825"},
{"Image Link": "https://images.brickset.com/sets/small/21055-1.jpg?202001090451"},
{"Image Link": "https://images.brickset.com/sets/small/21148-1.jpg?201812120846"},
{"Image Link": "https://images.brickset.com/sets/small/21149-1.jpg?201812120846"},
{"Image Link": "https://images.brickset.com/sets/small/21150-1.jpg?201812120846"},
{"Image Link": "/assets/images/misc/rlfm-white-logo.png"},
{"Image Link": "https://images.brickset.com/sets/small/21151-1.jpg?201812120846"},
{"Image Link": "https://images.brickset.com/sets/small/21152-1.jpg?201812120846"},
{"Image Link": "https://images.brickset.com/sets/small/21153-1.jpg?201907130955"},
{"Image Link": "https://images.brickset.com/sets/small/21154-1.jpg?201907130955"},
{"Image Link": "https://images.brickset.com/sets/small/21155-1.jpg?201907130955"},
{"Image Link": "https://images.brickset.com/sets/small/21316-1.jpg?201902200920"},
{"Image Link": "https://images.brickset.com/sets/small/21317-1.jpg?201903180157"},
{"Image Link": "https://images.brickset.com/sets/small/21318-1.jpg?201907230157"},
{"Image Link": "https://images.brickset.com/sets/small/21319-1.jpg?201908080158"},
{"Image Link": "https://images.brickset.com/sets/small/21320-1.jpg?201910160155"},
{"Image Link": "https://images.brickset.com/sets/small/30327-1.jpg?201901170834"},
{"Image Link": "https://images.brickset.com/sets/small/30328-0.jpg?201901170834"},
{"Image Link": "https://images.brickset.com/sets/small/30328-2.jpg?201901170844"},
{"Image Link": "https://images.brickset.com/sets/small/30328-3.jpg?201901170844"},
{"Image Link": "https://images.brickset.com/sets/small/30328-4.jpg?201901170844"},
{"Image Link": "https://images.brickset.com/sets/small/30328-5.jpg?201901170843"},
{"Image Link": "https://images.brickset.com/sets/small/30328-1.jpg?201901170843"},
{"Image Link": "https://images.brickset.com/sets/small/30340-1.jpg?201901270918"},
{"Image Link": "https://images.brickset.com/sets/small/30361-1.jpg?201901050928"},
{"Image Link": "https://images.brickset.com/sets/small/30362-1.jpg?201901060936"},
{"Image Link": "https://images.brickset.com/sets/small/30363-1.jpg?201901050914"},
{"Image Link": "https://images.brickset.com/sets/small/30364-1.jpg?201901050911"},
{"Image Link": "https://images.brickset.com/sets/small/30365-1.jpg?201905310930"},
{"Image Link": "https://images.brickset.com/sets/small/30383-1.jpg?201905310930"},
{"Image Link": "https://images.brickset.com/sets/small/30384-1.jpg?201904041247"},
{"Image Link": "/assets/images/misc/rlfm-white-logo.png"},
{"Image Link": "https://images.brickset.com/sets/small/30393-1.jpg?201901060921"},
{"Image Link": "https://images.brickset.com/sets/small/30408-1.jpg?201902200914"},
{"Image Link": "https://images.brickset.com/sets/small/30409-1.jpg?201812140830"},
{"Image Link": "https://images.brickset.com/sets/small/30410-1.jpg?201908050939"},
{"Image Link": "https://images.brickset.com/sets/small/30451-1.jpg?201907130955"},
{"Image Link": "https://images.brickset.com/sets/small/30452-1.jpg?201903270711"},
{"Image Link": "https://images.brickset.com/sets/small/30460-1.jpg?201901050104"},
{"Image Link": "https://images.brickset.com/sets/small/30461-1.jpg?201904041247"},
{"Image Link": "https://images.brickset.com/sets/small/30527-1.jpg?201901060937"},
{"Image Link": "https://images.brickset.com/sets/small/30528-1.jpg?201909251053"},
{"Image Link": "https://images.brickset.com/sets/small/30529-1.jpg?201902200914"},
{"Image Link": "https://images.brickset.com/sets/small/30533-1.jpg?201901050913"},
{"Image Link": "https://images.brickset.com/sets/small/30534-1.jpg?201901050236"},
{"Image Link": "https://images.brickset.com/sets/small/30535-1.jpg?201901060939"},
{"Image Link": "https://images.brickset.com/sets/small/30545-1.jpg?201902180225"},
{"Image Link": "https://images.brickset.com/sets/small/30553-1.jpg?201911131142"},
{"Image Link": "https://images.brickset.com/sets/small/30571-1.jpg?201901270918"},
{"Image Link": "https://images.brickset.com/sets/small/30572-1.jpg?201901050915"},
{"Image Link": "https://images.brickset.com/sets/small/30573-1.jpg?201912050921"},
{"Image Link": "https://images.brickset.com/sets/small/30620-1.jpg?201812140945"},
{"Image Link": "https://images.brickset.com/sets/small/30623-1.jpg?201905170810"},
{"Image Link": "https://images.brickset.com/sets/small/30624-1.jpg?201912050753"},
{"Image Link": "https://images.brickset.com/sets/small/31086-1.jpg?201811301044"},
{"Image Link": "https://images.brickset.com/sets/small/31087-1.jpg?201811301044"},
{"Image Link": "https://images.brickset.com/sets/small/31088-1.jpg?201811301044"},
{"Image Link": "/assets/images/misc/rlfm-white-logo.png"},
{"Image Link": "https://images.brickset.com/sets/small/31089-1.jpg?201811301044"},
{"Image Link": "https://images.brickset.com/sets/small/31090-1.jpg?201811301044"},
{"Image Link": "https://images.brickset.com/sets/small/31091-1.jpg?201811301044"},
{"Image Link": "https://images.brickset.com/sets/small/31092-1.jpg?201812041022"},
{"Image Link": "https://images.brickset.com/sets/small/31093-1.jpg?201812041022"},
{"Image Link": "https://images.brickset.com/sets/small/31094-1.jpg?201812041022"},
{"Image Link": "https://images.brickset.com/sets/small/31095-1.jpg?201905140825"},
{"Image Link": "https://images.brickset.com/sets/small/31096-1.jpg?201905140825"},
{"Image Link": "https://images.brickset.com/sets/small/31097-1.jpg?201905140825"},
{"Image Link": "https://images.brickset.com/sets/small/31098-1.jpg?201905140825"},
{"Image Link": "https://images.brickset.com/sets/small/40186-1.jpg?201901170834"},
{"Image Link": "https://images.brickset.com/sets/small/40318-1.jpg?201906090838"},
{"Image Link": "https://images.brickset.com/sets/small/40321-1.jpg?201901151057"},
{"Image Link": "https://images.brickset.com/sets/small/40322-1.jpg?201902061115"},
{"Image Link": "https://images.brickset.com/sets/small/40323-1.jpg?201902211101"},
{"Image Link": "https://images.brickset.com/sets/small/40324-1.jpg?201904010954"},
{"Image Link": "https://images.brickset.com/sets/small/40325-1.jpg?201905260414"},
{"Image Link": "https://images.brickset.com/sets/small/40326-1.jpg?201905260853"},
{"Image Link": "https://images.brickset.com/sets/small/40327-1.jpg?201907290313"},
{"Image Link": "https://images.brickset.com/sets/small/40328-1.jpg?201908011040"},
{"Image Link": "https://images.brickset.com/sets/small/40329-1.jpg?201909080307"},
{"Image Link": "https://images.brickset.com/sets/small/40330-1.jpg?201910010810"},
{"Image Link": "https://images.brickset.com/sets/small/40331-1.jpg?201911020901"},
{"Image Link": "https://images.brickset.com/sets/small/40332-1.jpg?201912011244"},
{"Image Link": "https://images.brickset.com/sets/small/40333-1.jpg?201904270648"},
{"Image Link": "/assets/images/misc/rlfm-white-logo.png"},
{"Image Link": "https://images.brickset.com/sets/small/40334-1.jpg?201904230852"},
{"Image Link": "https://images.brickset.com/sets/small/40335-1.jpg?201905130746"},
{"Image Link": "https://images.brickset.com/sets/small/40336-1.jpg?201907241243"},
{"Image Link": "https://images.brickset.com/sets/small/40337-1.jpg?201912051025"},
{"Image Link": "https://images.brickset.com/sets/small/40338-1.jpg?201911241006"},
{"Image Link": "https://images.brickset.com/sets/small/40341-1.jpg?201812050815"},
{"Image Link": "https://images.brickset.com/sets/small/40342-1.jpg?201905310930"},
{"Image Link": "https://images.brickset.com/sets/small/40343-1.jpg?201905310930"},
{"Image Link": "https://images.brickset.com/sets/small/40344-1.jpg?201905151200"},
{"Image Link": "https://images.brickset.com/sets/small/40345-1.jpg?201905310930"},
{"Image Link": "https://images.brickset.com/sets/small/40346-1.jpg?201905170922"},
{"Image Link": "https://images.brickset.com/sets/small/40347-1.jpg?201901051045"},
{"Image Link": "https://images.brickset.com/sets/small/40348-1.jpg?201812041022"},
{"Image Link": "https://images.brickset.com/sets/small/40349-1.jpg?201812041022"},
{"Image Link": "https://images.brickset.com/sets/small/40350-1.jpg?201901170834"},
{"Image Link": "https://images.brickset.com/sets/small/40351-1.jpg?201908161036"},
{"Image Link": "https://images.brickset.com/sets/small/40352-1.jpg?201910031017"},
{"Image Link": "https://images.brickset.com/sets/small/40353-1.jpg?201910031017"},
{"Image Link": "https://images.brickset.com/sets/small/40354-1.jpg?201812041022"},
{"Image Link": "https://images.brickset.com/sets/small/40356-1.jpg?201906111025"},
{"Image Link": "https://images.brickset.com/sets/small/40359-1.jpg?201812041022"},
{"Image Link": "https://images.brickset.com/sets/small/40360-1.jpg?201902200914"},
{"Image Link": "https://images.brickset.com/sets/small/40361-1.jpg?201911131142"},
{"Image Link": "https://images.brickset.com/sets/small/40362-1.jpg?201910031017"},
{"Image Link": "https://images.brickset.com/sets/small/40366-1.jpg?202005071010"},
{"Image Link": "/assets/images/misc/rlfm-white-logo.png"},
{"Image Link": "https://images.brickset.com/sets/small/40367-1.jpg?201905140825"},
{"Image Link": "https://images.brickset.com/sets/small/40368-1.jpg?201910031017"},
{"Image Link": "https://images.brickset.com/sets/small/40432-1.jpg?201909120259"},
{"Image Link": "https://images.brickset.com/sets/small/40433-1.jpg?201911070652"},
{"Image Link": "https://images.brickset.com/sets/small/40434-1.jpg?201911051053"},
{"Image Link": "https://images.brickset.com/sets/small/40435-1.jpg?202005280441"},
{"Image Link": "https://images.brickset.com/sets/small/41158-1.jpg?201812140830"},
{"Image Link": "https://images.brickset.com/sets/small/41159-1.jpg?201812140830"},
{"Image Link": "https://images.brickset.com/sets/small/41160-1.jpg?201812140830"},
{"Image Link": "https://images.brickset.com/sets/small/41161-1.jpg?201812140830"},
{"Image Link": "https://images.brickset.com/sets/small/41162-1.jpg?201812140830"},
{"Image Link": "https://images.brickset.com/sets/small/41163-1.jpg?201812140830"},
{"Image Link": "https://images.brickset.com/sets/small/41164-1.jpg?201910031017"},
{"Image Link": "https://images.brickset.com/sets/small/41165-1.jpg?201910031017"},
{"Image Link": "https://images.brickset.com/sets/small/41166-1.jpg?201910031017"},
{"Image Link": "https://images.brickset.com/sets/small/41167-1.jpg?201910031017"},
{"Image Link": "https://images.brickset.com/sets/small/41168-1.jpg?201910031017"},
{"Image Link": "https://images.brickset.com/sets/small/41169-1.jpg?201910031017"},
{"Image Link": "https://images.brickset.com/sets/small/41337-1.jpg?201906120130"},
{"Image Link": "https://images.brickset.com/sets/small/41354-1.jpg?201812041022"},
{"Image Link": "https://images.brickset.com/sets/small/41355-1.jpg?201812041022"},
{"Image Link": "https://images.brickset.com/sets/small/41356-1.jpg?201812041022"},
{"Image Link": "https://images.brickset.com/sets/small/41357-1.jpg?201812041022"},
{"Image Link": "https://images.brickset.com/sets/small/41358-1.jpg?201812041022"},
{"Image Link": "https://images.brickset.com/sets/small/41359-1.jpg?201812041022"},
{"Image Link": "/assets/images/misc/rlfm-white-logo.png"},
{"Image Link": "https://images.brickset.com/sets/small/41360-1.jpg?201812041022"},
{"Image Link": "https://images.brickset.com/sets/small/41361-1.jpg?201812041022"},
{"Image Link": "https://images.brickset.com/sets/small/41362-1.jpg?201905140825"},
{"Image Link": "https://images.brickset.com/sets/small/41363-1.jpg?201812041022"},
{"Image Link": "https://images.brickset.com/sets/small/41364-1.jpg?201811301044"},
{"Image Link": "https://images.brickset.com/sets/small/41365-1.jpg?201811301044"},
{"Image Link": "https://images.brickset.com/sets/small/41366-1.jpg?201811301044"},
{"Image Link": "https://images.brickset.com/sets/small/41367-1.jpg?201812041022"},
{"Image Link": "https://images.brickset.com/sets/small/41368-1.jpg?201812041022"},
{"Image Link": "https://images.brickset.com/sets/small/41369-1.jpg?201812041022"},
{"Image Link": "https://images.brickset.com/sets/small/41371-1.jpg?201905140825"},
{"Image Link": "https://images.brickset.com/sets/small/41372-1.jpg?201905140825"},
{"Image Link": "https://images.brickset.com/sets/small/41373-1.jpg?201905140825"},
{"Image Link": "https://images.brickset.com/sets/small/41374-1.jpg?201905140825"},
{"Image Link": "https://images.brickset.com/sets/small/41375-1.jpg?201905140825"},
{"Image Link": "https://images.brickset.com/sets/small/41376-1.jpg?201905140825"},
{"Image Link": "https://images.brickset.com/sets/small/41378-1.jpg?201905140825"},
{"Image Link": "https://images.brickset.com/sets/small/41379-1.jpg?201905140825"},
{"Image Link": "https://images.brickset.com/sets/small/41380-1.jpg?201905140825"},
{"Image Link": "https://images.brickset.com/sets/small/41381-1.jpg?201905140825"},
{"Image Link": "https://images.brickset.com/sets/small/41382-1.jpg?201908161036"},
{"Image Link": "https://images.brickset.com/sets/small/41383-1.jpg?201812041022"},
{"Image Link": "https://images.brickset.com/sets/small/41384-1.jpg?201905140825"},
{"Image Link": "https://images.brickset.com/sets/small/41385-1.jpg?201905140825"},
{"Image Link": "https://images.brickset.com/sets/small/41386-1.jpg?201905140825"},
{"Image Link": "/assets/images/misc/rlfm-white-logo.png"},
{"Image Link": "https://images.brickset.com/sets/small/41387-1.jpg?201905140825"},
{"Image Link": "https://images.brickset.com/sets/small/41388-1.jpg?201905140825"},
{"Image Link": "https://images.brickset.com/sets/small/41634-1.jpg?201902071155"},
{"Image Link": "https://images.brickset.com/sets/small/41635-1.jpg?201902071155"},
{"Image Link": "https://images.brickset.com/sets/small/41636-1.jpg?201902081028"},
{"Image Link": "https://images.brickset.com/sets/small/41637-1.jpg?201902081028"},
{"Image Link": "https://images.brickset.com/sets/small/42088-1.jpg?201812041022"},
{"Image Link": "https://images.brickset.com/sets/small/42089-1.jpg?201811291125"},
{"Image Link": "https://images.brickset.com/sets/small/42090-1.jpg?201811291125"},
{"Image Link": "https://images.brickset.com/sets/small/42091-1.jpg?201811291126"},
{"Image Link": "https://images.brickset.com/sets/small/42092-1.jpg?201811291126"},
{"Image Link": "https://images.brickset.com/sets/small/42093-1.jpg?201812041022"},
{"Image Link": "https://images.brickset.com/sets/small/42094-1.jpg?201812041022"},
{"Image Link": "https://images.brickset.com/sets/small/42095-1.jpg?201812041022"},
{"Image Link": "https://images.brickset.com/sets/small/42096-1.jpg?201812041022"},
{"Image Link": "https://images.brickset.com/sets/small/42097-1.jpg?201907130955"},
{"Image Link": "https://images.brickset.com/sets/small/42098-1.jpg?201907130955"},
{"Image Link": "https://images.brickset.com/sets/small/42099-1.jpg?201907130955"},
{"Image Link": "https://images.brickset.com/sets/small/42100-1.jpg?201909251053"},
{"Image Link": "https://images.brickset.com/sets/small/42110-1.jpg?201909101054"},
{"Image Link": "https://images.brickset.com/sets/small/43172-1.jpg?201907130955"},
{"Image Link": "/assets/images/misc/blankbox.gif"},
{"Image Link": "https://images.brickset.com/sets/small/45810-1.jpg?202009250145"},
{"Image Link": "https://images.brickset.com/sets/small/60203-1.jpg?201908161036"},
{"Image Link": "https://images.brickset.com/sets/small/60206-1.jpg?201811301044"},
{"Image Link": "/assets/images/misc/rlfm-white-logo.png"},
{"Image Link": "https://images.brickset.com/sets/small/60207-1.jpg?201811301044"},
{"Image Link": "https://images.brickset.com/sets/small/60208-1.jpg?201812041022"},
{"Image Link": "https://images.brickset.com/sets/small/60209-1.jpg?201812041022"},
{"Image Link": "https://images.brickset.com/sets/small/60210-1.jpg?201812041022"},
{"Image Link": "https://images.brickset.com/sets/small/60212-1.jpg?201811301044"},
{"Image Link": "https://images.brickset.com/sets/small/60213-1.jpg?201811301044"},
{"Image Link": "https://images.brickset.com/sets/small/60214-1.jpg?201812041022"},
{"Image Link": "https://images.brickset.com/sets/small/60215-1.jpg?201812041022"},
{"Image Link": "https://images.brickset.com/sets/small/60216-1.jpg?201812041022"},
{"Image Link": "https://images.brickset.com/sets/small/60217-1.jpg?201812041022"},
{"Image Link": "https://images.brickset.com/sets/small/60218-1.jpg?201811301044"},
{"Image Link": "https://images.brickset.com/sets/small/60219-1.jpg?201811301044"},
{"Image Link": "https://images.brickset.com/sets/small/60220-1.jpg?201811301044"},
{"Image Link": "https://images.brickset.com/sets/small/60221-1.jpg?201811301044"},
{"Image Link": "https://images.brickset.com/sets/small/60222-1.jpg?201811301044"},
{"Image Link": "https://images.brickset.com/sets/small/60223-1.jpg?201811301044"},
{"Image Link": "https://images.brickset.com/sets/small/60224-1.jpg?201905140825"},
{"Image Link": "https://images.brickset.com/sets/small/60225-1.jpg?201905140825"},
{"Image Link": "https://images.brickset.com/sets/small/60226-1.jpg?201905140825"},
{"Image Link": "https://images.brickset.com/sets/small/60227-1.jpg?201905140825"},
{"Image Link": "https://images.brickset.com/sets/small/60228-1.jpg?201905140825"},
{"Image Link": "https://images.brickset.com/sets/small/60229-1.jpg?201905140825"},
{"Image Link": "https://images.brickset.com/sets/small/60230-1.jpg?201905140825"},
{"Image Link": "https://images.brickset.com/sets/small/60231-1.jpg?201905140825"},
{"Image Link": "https://images.brickset.com/sets/small/60232-1.jpg?201905140825"},
{"Image Link": "/assets/images/misc/rlfm-white-logo.png"},
{"Image Link": "https://images.brickset.com/sets/small/60233-1.jpg?201905140825"},
{"Image Link": "https://images.brickset.com/sets/small/60234-1.jpg?201905140825"},
{"Image Link": "https://images.brickset.com/sets/small/60235-1.jpg?201908161036"},
{"Image Link": "https://images.brickset.com/sets/small/60236-1.jpg?201812041022"},
{"Image Link": "https://images.brickset.com/sets/small/60237-1.jpg?201812041022"},
{"Image Link": "https://images.brickset.com/sets/small/60239-1.jpg?201812041022"},
{"Image Link": "https://images.brickset.com/sets/small/60240-1.jpg?201812041022"},
{"Image Link": "/assets/images/misc/blankbox.gif"},
{"Image Link": "/assets/images/misc/blankbox.gif"},
{"Image Link": "/assets/images/misc/blankbox.gif"},
{"Image Link": "/assets/images/misc/blankbox.gif"},
{"Image Link": "/assets/images/misc/blankbox.gif"},
{"Image Link": "https://images.brickset.com/sets/small/66593-1.jpg?201906120820"},
{"Image Link": "https://images.brickset.com/sets/small/66615-1.jpg?201910220835"},
{"Image Link": "https://images.brickset.com/sets/small/66619-1.jpg?201909251030"},
{"Image Link": "https://images.brickset.com/sets/small/66620-1.jpg?201909251030"},
{"Image Link": "https://images.brickset.com/sets/small/70418-1.jpg?201906150837"},
{"Image Link": "https://images.brickset.com/sets/small/70419-1.jpg?201906150837"},
{"Image Link": "https://images.brickset.com/sets/small/70420-1.jpg?201906150837"},
{"Image Link": "https://images.brickset.com/sets/small/70421-1.jpg?201906150837"},
{"Image Link": "https://images.brickset.com/sets/small/70422-1.jpg?201906150837"},
{"Image Link": "https://images.brickset.com/sets/small/70423-1.jpg?201906150837"},
{"Image Link": "https://images.brickset.com/sets/small/70424-1.jpg?201906150837"},
{"Image Link": "https://images.brickset.com/sets/small/70425-1.jpg?201906150837"},
{"Image Link": "https://images.brickset.com/sets/small/70659-1.jpg?201812120846"},
{"Image Link": "/assets/images/misc/rlfm-white-logo.png"},
{"Image Link": "https://images.brickset.com/sets/small/70660-1.jpg?201812120846"},
{"Image Link": "https://images.brickset.com/sets/small/70661-1.jpg?201812120846"},
{"Image Link": "https://images.brickset.com/sets/small/70662-1.jpg?201812120846"},
{"Image Link": "https://images.brickset.com/sets/small/70663-1.jpg?201812120846"},
{"Image Link": "https://images.brickset.com/sets/small/70664-1.jpg?201812120846"},
{"Image Link": "https://images.brickset.com/sets/small/70665-1.jpg?201812120846"},
{"Image Link": "https://images.brickset.com/sets/small/70666-1.jpg?201812120846"},
{"Image Link": "https://images.brickset.com/sets/small/70667-1.jpg?201812120846"},
{"Image Link": "https://images.brickset.com/sets/small/70668-1.jpg?201812120846"},
{"Image Link": "https://images.brickset.com/sets/small/70669-1.jpg?201812120846"},
{"Image Link": "https://images.brickset.com/sets/small/70670-1.jpg?201812120846"},
{"Image Link": "https://images.brickset.com/sets/small/70671-1.jpg?201905140825"},
{"Image Link": "https://images.brickset.com/sets/small/70672-1.jpg?201905140825"},
{"Image Link": "https://images.brickset.com/sets/small/70673-1.jpg?201905140825"},
{"Image Link": "https://images.brickset.com/sets/small/70674-1.jpg?201905140825"},
{"Image Link": "https://images.brickset.com/sets/small/70675-1.jpg?201905140825"},
{"Image Link": "https://images.brickset.com/sets/small/70676-1.jpg?201905140825"},
{"Image Link": "https://images.brickset.com/sets/small/70677-1.jpg?201905140825"},
{"Image Link": "https://images.brickset.com/sets/small/70678-1.jpg?201905140825"},
{"Image Link": "https://images.brickset.com/sets/small/70679-1.jpg?201812120846"},
{"Image Link": "https://images.brickset.com/sets/small/70680-1.jpg?201812120846"},
{"Image Link": "https://images.brickset.com/sets/small/70681-1.jpg?201905140825"},
{"Image Link": "https://images.brickset.com/sets/small/70682-1.jpg?201905140825"},
{"Image Link": "https://images.brickset.com/sets/small/70683-1.jpg?201905140825"},
{"Image Link": "https://images.brickset.com/sets/small/70684-1.jpg?201905140825"},
{"Image Link": "/assets/images/misc/rlfm-white-logo.png"},
{"Image Link": "https://images.brickset.com/sets/small/70820-1.jpg?201811200650"},
{"Image Link": "https://images.brickset.com/sets/small/70821-1.jpg?201811200644"},
{"Image Link": "https://images.brickset.com/sets/small/70822-1.jpg?201811200647"},
{"Image Link": "https://images.brickset.com/sets/small/70823-1.jpg?201811200645"},
{"Image Link": "https://images.brickset.com/sets/small/70824-1.jpg?201811200628"},
{"Image Link": "https://images.brickset.com/sets/small/70825-1.jpg?201811200628"},
{"Image Link": "https://images.brickset.com/sets/small/70826-1.jpg?201811200627"},
{"Image Link": "https://images.brickset.com/sets/small/70827-1.jpg?201901050930"},
{"Image Link": "https://images.brickset.com/sets/small/70828-1.jpg?201811200622"},
{"Image Link": "https://images.brickset.com/sets/small/70829-1.jpg?201811200633"},
{"Image Link": "https://images.brickset.com/sets/small/70830-1.jpg?201901250420"},
{"Image Link": "https://images.brickset.com/sets/small/70831-1.jpg?201811200619"},
{"Image Link": "https://images.brickset.com/sets/small/70832-1.jpg?201811200620"},
{"Image Link": "https://images.brickset.com/sets/small/70833-1.jpg?201811200620"},
{"Image Link": "https://images.brickset.com/sets/small/70834-1.jpg?201811200610"},
{"Image Link": "https://images.brickset.com/sets/small/70835-1.jpg?201811200613"},
{"Image Link": "https://images.brickset.com/sets/small/70836-1.jpg?201811200616"},
{"Image Link": "https://images.brickset.com/sets/small/70837-1.jpg?201904270648"},
{"Image Link": "https://images.brickset.com/sets/small/70838-1.jpg?201904270648"},
{"Image Link": "https://images.brickset.com/sets/small/70839-1.jpg?201904270648"},
{"Image Link": "https://images.brickset.com/sets/small/70840-1.jpg?201901061157"},
{"Image Link": "https://images.brickset.com/sets/small/70841-1.jpg?201811200607"},
{"Image Link": "https://images.brickset.com/sets/small/70842-1.jpg?201904270648"},
{"Image Link": "https://images.brickset.com/sets/small/70847-1.jpg?201907130955"},
{"Image Link": "https://images.brickset.com/sets/small/70848-1.jpg?201907130955"},
{"Image Link": "/assets/images/misc/rlfm-white-logo.png"},
{"Image Link": "https://images.brickset.com/sets/small/70849-1.jpg?201907130955"},
{"Image Link": "https://images.brickset.com/sets/small/71023-0.jpg?201901150202"},
{"Image Link": "https://images.brickset.com/sets/small/71023-1.jpg?201901150203"},
{"Image Link": "https://images.brickset.com/sets/small/71023-2.jpg?201901150203"},
{"Image Link": "https://images.brickset.com/sets/small/71023-8.jpg?201901150204"},
{"Image Link": "https://images.brickset.com/sets/small/71023-5.jpg?201901150204"},
{"Image Link": "https://images.brickset.com/sets/small/71023-4.jpg?201901150203"},
{"Image Link": "https://images.brickset.com/sets/small/71023-7.jpg?201901150204"},
{"Image Link": "https://images.brickset.com/sets/small/71023-20.jpg?201901150207"},
{"Image Link": "https://images.brickset.com/sets/small/71023-6.jpg?201901150204"},
{"Image Link": "https://images.brickset.com/sets/small/71023-15.jpg?201901150206"},
{"Image Link": "https://images.brickset.com/sets/small/71023-3.jpg?201901150203"},
{"Image Link": "https://images.brickset.com/sets/small/71023-16.jpg?201901150206"},
{"Image Link": "https://images.brickset.com/sets/small/71023-14.jpg?201901150206"},
{"Image Link": "https://images.brickset.com/sets/small/71023-18.jpg?201901150206"},
{"Image Link": "https://images.brickset.com/sets/small/71023-9.jpg?201901150204"},
{"Image Link": "https://images.brickset.com/sets/small/71023-17.jpg?201901150206"},
{"Image Link": "https://images.brickset.com/sets/small/71023-10.jpg?201901150205"},
{"Image Link": "https://images.brickset.com/sets/small/71023-11.jpg?201901150205"},
{"Image Link": "https://images.brickset.com/sets/small/71023-13.jpg?201901150205"},
{"Image Link": "https://images.brickset.com/sets/small/71023-12.jpg?201901150205"},
{"Image Link": "https://images.brickset.com/sets/small/71023-19.jpg?201901150206"},
{"Image Link": "https://images.brickset.com/sets/small/71023-21.jpg?201901150207"},
{"Image Link": "https://images.brickset.com/sets/small/71023-22.jpg?201901150207"},
{"Image Link": "https://images.brickset.com/sets/small/71024-0.jpg?201903270710"},
{"Image Link": "/assets/images/misc/rlfm-white-logo.png"},
{"Image Link": "https://images.brickset.com/sets/small/71024-1.jpg?201903200256"},
{"Image Link": "https://images.brickset.com/sets/small/71024-2.jpg?201903200256"},
{"Image Link": "https://images.brickset.com/sets/small/71024-4.jpg?201903200257"},
{"Image Link": "https://images.brickset.com/sets/small/71024-5.jpg?201903200257"},
{"Image Link": "https://images.brickset.com/sets/small/71024-6.jpg?201903200257"},
{"Image Link": "https://images.brickset.com/sets/small/71024-3.jpg?201903200256"},
{"Image Link": "https://images.brickset.com/sets/small/71024-7.jpg?201903200257"},
{"Image Link": "https://images.brickset.com/sets/small/71024-8.jpg?201903200257"},
{"Image Link": "https://images.brickset.com/sets/small/71024-12.jpg?201903200259"},
{"Image Link": "https://images.brickset.com/sets/small/71024-11.jpg?201903200259"},
{"Image Link": "https://images.brickset.com/sets/small/71024-10.jpg?201903200258"},
{"Image Link": "https://images.brickset.com/sets/small/71024-9.jpg?201903200258"},
{"Image Link": "https://images.brickset.com/sets/small/71024-18.jpg?201903200300"},
{"Image Link": "https://images.brickset.com/sets/small/71024-17.jpg?201903200300"},
{"Image Link": "https://images.brickset.com/sets/small/71024-14.jpg?201903200259"},
{"Image Link": "https://images.brickset.com/sets/small/71024-13.jpg?201903200259"},
{"Image Link": "https://images.brickset.com/sets/small/71024-15.jpg?201903200259"},
{"Image Link": "https://images.brickset.com/sets/small/71024-16.jpg?201903200300"},
{"Image Link": "https://images.brickset.com/sets/small/71024-19.jpg?201903200300"},
{"Image Link": "https://images.brickset.com/sets/small/71024-20.jpg?201903200300"},
{"Image Link": "https://images.brickset.com/sets/small/71025-0.jpg?201908010213"},
{"Image Link": "https://images.brickset.com/sets/small/71025-1.jpg?201909090219"},
{"Image Link": "https://images.brickset.com/sets/small/71025-2.jpg?201909090219"},
{"Image Link": "https://images.brickset.com/sets/small/71025-3.jpg?201909090219"},
{"Image Link": "https://images.brickset.com/sets/small/71025-4.jpg?201909090220"},
{"Image Link": "/assets/images/misc/rlfm-white-logo.png"},
{"Image Link": "https://images.brickset.com/sets/small/71025-5.jpg?201909090220"},
{"Image Link": "https://images.brickset.com/sets/small/71025-6.jpg?201909090220"},
{"Image Link": "https://images.brickset.com/sets/small/71025-7.jpg?201909090221"},
{"Image Link": "https://images.brickset.com/sets/small/71025-8.jpg?201909090221"},
{"Image Link": "https://images.brickset.com/sets/small/71025-9.jpg?201909090221"},
{"Image Link": "https://images.brickset.com/sets/small/71025-10.jpg?201909090221"},
{"Image Link": "https://images.brickset.com/sets/small/71025-11.jpg?201909090222"},
{"Image Link": "https://images.brickset.com/sets/small/71025-12.jpg?201909090222"},
{"Image Link": "https://images.brickset.com/sets/small/71025-13.jpg?201909090225"},
{"Image Link": "https://images.brickset.com/sets/small/71025-14.jpg?201909090225"},
{"Image Link": "https://images.brickset.com/sets/small/71025-15.jpg?201909090223"},
{"Image Link": "https://images.brickset.com/sets/small/71025-16.jpg?201909090223"},
{"Image Link": "https://images.brickset.com/sets/small/71025-17.jpg?201908010328"},
{"Image Link": "https://images.brickset.com/sets/small/71025-18.jpg?201908010216"},
{"Image Link": "https://images.brickset.com/sets/small/71044-1.jpg?201908130159"},
{"Image Link": "https://images.brickset.com/sets/small/75223-1.jpg?201812140830"},
{"Image Link": "https://images.brickset.com/sets/small/75224-1.jpg?201812140830"},
{"Image Link": "https://images.brickset.com/sets/small/75225-1.jpg?201812140830"},
{"Image Link": "https://images.brickset.com/sets/small/75226-1.jpg?201812140830"},
{"Image Link": "https://images.brickset.com/sets/small/75227-1.jpg?201903210724"},
{"Image Link": "https://images.brickset.com/sets/small/75228-1.jpg?201812140830"},
{"Image Link": "https://images.brickset.com/sets/small/75229-1.jpg?201812140830"},
{"Image Link": "https://images.brickset.com/sets/small/75232-1.jpg?201910040825"},
{"Image Link": "https://images.brickset.com/sets/small/75233-1.jpg?201812140830"},
{"Image Link": "https://images.brickset.com/sets/small/75234-1.jpg?201812140830"},
{"Image Link": "/assets/images/misc/rlfm-white-logo.png"},
{"Image Link": "https://images.brickset.com/sets/small/75235-1.jpg?201812140830"},
{"Image Link": "https://images.brickset.com/sets/small/75236-1.jpg?201903210341"},
{"Image Link": "https://images.brickset.com/sets/small/75237-1.jpg?201812140830"},
{"Image Link": "https://images.brickset.com/sets/small/75238-1.jpg?201903210341"},
{"Image Link": "https://images.brickset.com/sets/small/75239-1.jpg?201903210341"},
{"Image Link": "https://images.brickset.com/sets/small/75240-1.jpg?201903210341"},
{"Image Link": "https://images.brickset.com/sets/small/75241-1.jpg?201903210341"},
{"Image Link": "https://images.brickset.com/sets/small/75242-1.jpg?201903210341"},
{"Image Link": "https://images.brickset.com/sets/small/75243-1.jpg?201903210341"},
{"Image Link": "https://images.brickset.com/sets/small/75244-1.jpg?201904120858"},
{"Image Link": "https://images.brickset.com/sets/small/75245-1.jpg?202004191234"},
{"Image Link": "https://images.brickset.com/sets/small/75246-1.jpg?201910040825"},
{"Image Link": "https://images.brickset.com/sets/small/75247-1.jpg?201812140830"},
{"Image Link": "https://images.brickset.com/sets/small/75248-1.jpg?201910040825"},
{"Image Link": "https://images.brickset.com/sets/small/75249-1.jpg?201910040825"},
{"Image Link": "https://images.brickset.com/sets/small/75250-1.jpg?201910040825"},
{"Image Link": "https://images.brickset.com/sets/small/75251-1.jpg?201810030922"},
{"Image Link": "https://images.brickset.com/sets/small/75252-1.jpg?201909050158"},
{"Image Link": "https://images.brickset.com/sets/small/75253-1.jpg?201905300148"},
{"Image Link": "https://images.brickset.com/sets/small/75254-1.jpg?201910040825"},
{"Image Link": "https://images.brickset.com/sets/small/75255-1.jpg?201910040825"},
{"Image Link": "https://images.brickset.com/sets/small/75256-1.jpg?201910040825"},
{"Image Link": "https://images.brickset.com/sets/small/75257-1.jpg?201910040825"},
{"Image Link": "https://images.brickset.com/sets/small/75258-1.jpg?201903210341"},
{"Image Link": "https://images.brickset.com/sets/small/75259-1.jpg?201903210341"},
{"Image Link": "/assets/images/misc/rlfm-white-logo.png"},
{"Image Link": "https://images.brickset.com/sets/small/75261-1.jpg?201903210341"},
{"Image Link": "https://images.brickset.com/sets/small/75262-1.jpg?201903210341"},
{"Image Link": "https://images.brickset.com/sets/small/75522-1.jpg?201909080958"},
{"Image Link": "https://images.brickset.com/sets/small/75810-1.jpg?201905141159"},
{"Image Link": "https://images.brickset.com/sets/small/75890-1.jpg?201812041022"},
{"Image Link": "https://images.brickset.com/sets/small/75891-1.jpg?201812041022"},
{"Image Link": "https://images.brickset.com/sets/small/75892-1.jpg?201812041022"},
{"Image Link": "https://images.brickset.com/sets/small/75893-1.jpg?201812041022"},
{"Image Link": "https://images.brickset.com/sets/small/75894-1.jpg?201812041022"},
{"Image Link": "https://images.brickset.com/sets/small/75895-1.jpg?201907130955"},
{"Image Link": "https://images.brickset.com/sets/small/75934-1.jpg?201905140825"},
{"Image Link": "https://images.brickset.com/sets/small/75935-1.jpg?201905140825"},
{"Image Link": "https://images.brickset.com/sets/small/75936-1.jpg?201906110158"},
{"Image Link": "https://images.brickset.com/sets/small/75937-1.jpg?201905140825"},
{"Image Link": "https://images.brickset.com/sets/small/75938-1.jpg?201905140825"},
{"Image Link": "https://images.brickset.com/sets/small/75945-1.jpg?201905140825"},
{"Image Link": "https://images.brickset.com/sets/small/75946-1.jpg?201905140825"},
{"Image Link": "https://images.brickset.com/sets/small/75947-1.jpg?201905140825"},
{"Image Link": "https://images.brickset.com/sets/small/75948-1.jpg?201905140825"},
{"Image Link": "https://images.brickset.com/sets/small/75957-1.jpg?201905140825"},
{"Image Link": "https://images.brickset.com/sets/small/75958-1.jpg?201907130955"},
{"Image Link": "https://images.brickset.com/sets/small/75964-1.jpg?201911251110"},
{"Image Link": "https://images.brickset.com/sets/small/75965-1.jpg?201907130955"},
{"Image Link": "https://images.brickset.com/sets/small/75970-1.jpg?201811021112"},
{"Image Link": "https://images.brickset.com/sets/small/75971-1.jpg?201811021112"},
{"Image Link": "/assets/images/misc/rlfm-white-logo.png"},
{"Image Link": "https://images.brickset.com/sets/small/75972-1.jpg?201811021112"},
{"Image Link": "https://images.brickset.com/sets/small/75973-1.jpg?201811021112"},
{"Image Link": "https://images.brickset.com/sets/small/75974-1.jpg?201811021112"},
{"Image Link": "https://images.brickset.com/sets/small/75975-1.jpg?201811021112"},
{"Image Link": "https://images.brickset.com/sets/small/75976-1.jpg?201907130955"},
{"Image Link": "https://images.brickset.com/sets/small/75977-1.jpg?201907130955"},
{"Image Link": "https://images.brickset.com/sets/small/76113-1.jpg?201811201001"},
{"Image Link": "https://images.brickset.com/sets/small/76114-1.jpg?201811201001"},
{"Image Link": "https://images.brickset.com/sets/small/76115-1.jpg?201811201001"},
{"Image Link": "https://images.brickset.com/sets/small/76116-1.jpg?201812140830"},
{"Image Link": "https://images.brickset.com/sets/small/76117-1.jpg?201812140830"},
{"Image Link": "https://images.brickset.com/sets/small/76118-1.jpg?201905140825"},
{"Image Link": "https://images.brickset.com/sets/small/76119-1.jpg?201905140825"},
{"Image Link": "https://images.brickset.com/sets/small/76120-1.jpg?201905140825"},
{"Image Link": "https://images.brickset.com/sets/small/76122-1.jpg?201905140825"},
{"Image Link": "https://images.brickset.com/sets/small/76123-1.jpg?201904040109"},
{"Image Link": "https://images.brickset.com/sets/small/76124-1.jpg?201904040109"},
{"Image Link": "https://images.brickset.com/sets/small/76125-1.jpg?201904040109"},
{"Image Link": "https://images.brickset.com/sets/small/76126-1.jpg?201904040109"},
{"Image Link": "https://images.brickset.com/sets/small/76127-1.jpg?201812140830"},
{"Image Link": "https://images.brickset.com/sets/small/76128-1.jpg?201904230852"},
{"Image Link": "https://images.brickset.com/sets/small/76129-1.jpg?201904230852"},
{"Image Link": "https://images.brickset.com/sets/small/76130-1.jpg?201904230852"},
{"Image Link": "https://images.brickset.com/sets/small/76131-1.jpg?201904040109"},
{"Image Link": "https://images.brickset.com/sets/small/76133-1.jpg?201811201001"},
{"Image Link": "/assets/images/misc/rlfm-white-logo.png"},
{"Image Link": "https://images.brickset.com/sets/small/76134-1.jpg?201811201001"},
{"Image Link": "https://images.brickset.com/sets/small/76137-1.jpg?201905140825"},
{"Image Link": "https://images.brickset.com/sets/small/76138-1.jpg?201905140825"},
{"Image Link": "https://images.brickset.com/sets/small/76139-1.jpg?201911070159"},
{"Image Link": "https://images.brickset.com/sets/small/76144-1.jpg?201911241006"},
{"Image Link": "https://images.brickset.com/sets/small/77901-1.jpg?201907101010"},
{"Image Link": "https://images.brickset.com/sets/small/77902-1.jpg?201906170354"},
{"Image Link": "https://images.brickset.com/sets/small/77903-1.jpg?201906190442"},
{"Image Link": "https://images.brickset.com/sets/small/80101-1.jpg?201812140830"},
{"Image Link": "https://images.brickset.com/sets/small/80102-1.jpg?201812140830"},
{"Image Link": "https://images.brickset.com/sets/small/80103-1.jpg?201904260807"},
{"Image Link": "https://images.brickset.com/sets/small/81000-1.jpg?201907130935"},
{"Image Link": "https://images.brickset.com/sets/small/81001-1.jpg?201809271048"},
{"Image Link": "https://images.brickset.com/sets/small/81002-1.jpg?201809271050"},
{"Image Link": "https://images.brickset.com/sets/small/81003-1.jpg?201809270851"},
{"Image Link": "https://images.brickset.com/sets/small/88006-1.jpg?201812051059"},
{"Image Link": "https://images.brickset.com/sets/small/88007-1.jpg?201812051059"},
{"Image Link": "https://images.brickset.com/sets/small/88008-1.jpg?201812051059"},
{"Image Link": "https://images.brickset.com/sets/small/88009-1.jpg?201812051059"},
{"Image Link": "https://images.brickset.com/sets/small/88010-1.jpg?201812051059"},
{"Image Link": "https://images.brickset.com/sets/small/88011-1.jpg?201812051059"},
{"Image Link": "https://images.brickset.com/sets/small/111901-1.jpg?201904280920"},
{"Image Link": "https://images.brickset.com/sets/small/111901-2.jpg?201909190852"},
{"Image Link": "https://images.brickset.com/sets/small/111902-1.jpg?201909190852"},
{"Image Link": "https://images.brickset.com/sets/small/111902-2.jpg?201909190852"},
{"Image Link": "/assets/images/misc/rlfm-white-logo.png"},
{"Image Link": "https://images.brickset.com/sets/small/111903-1.jpg?201909190853"},
{"Image Link": "https://images.brickset.com/sets/small/111903-2.jpg?201909190853"},
{"Image Link": "https://images.brickset.com/sets/small/111904-1.jpg?201911290920"},
{"Image Link": "https://images.brickset.com/sets/small/111904-2.jpg?201911270731"},
{"Image Link": "https://images.brickset.com/sets/small/121903-1.jpg?201905310904"},
{"Image Link": "https://images.brickset.com/sets/small/121904-1.jpg?201910020854"},
{"Image Link": "https://images.brickset.com/sets/small/BAT211901-1.jpg?201902040847"},
{"Image Link": "https://images.brickset.com/sets/small/211902-1.jpg?201904250831"},
{"Image Link": "https://images.brickset.com/sets/small/211903-1.jpg?201905170812"},
{"Image Link": "https://images.brickset.com/sets/small/211904-1.jpg?201907220853"},
{"Image Link": "https://images.brickset.com/sets/small/211905-1.jpg?201909190854"},
{"Image Link": "https://images.brickset.com/sets/small/211906-1.jpg?201911200854"},
{"Image Link": "https://images.brickset.com/sets/small/471904-1.jpg?201907130933"},
{"Image Link": "https://images.brickset.com/sets/small/TLM471905-1.jpg?201901250420"},
{"Image Link": "https://images.brickset.com/sets/small/TLM471906-1.jpg?201903180946"},
{"Image Link": "https://images.brickset.com/sets/small/FR561901-1.jpg?201901270843"},
{"Image Link": "https://images.brickset.com/sets/small/FR561902-1.jpg?201903030844"},
{"Image Link": "https://images.brickset.com/sets/small/561903-1.jpg?201905310903"},
{"Image Link": "https://images.brickset.com/sets/small/561904-1.jpg?201904060344"},
{"Image Link": "https://images.brickset.com/sets/small/561905-1.jpg?201908240848"},
{"Image Link": "https://images.brickset.com/sets/small/561906-1.jpg?201906151200"},
{"Image Link": "https://images.brickset.com/sets/small/561907-1.jpg?201909120908"},
{"Image Link": "https://images.brickset.com/sets/small/561908-1.jpg?201909190854"},
{"Image Link": "https://images.brickset.com/sets/small/561909-1.jpg?201909190854"},
{"Image Link": "https://images.brickset.com/sets/small/561910-1.jpg?201911051050"},
{"Image Link": "/assets/images/misc/rlfm-white-logo.png"},
{"Image Link": "https://images.brickset.com/sets/small/561911-1.jpg?201911140941"},
{"Image Link": "https://images.brickset.com/sets/small/791901-1.jpg?201909210347"},
{"Image Link": "https://images.brickset.com/sets/small/791902-1.jpg?201911070732"},
{"Image Link": "https://images.brickset.com/sets/small/791903-1.jpg?201912210756"},
{"Image Link": "https://images.brickset.com/sets/small/853865-1.jpg?201902200914"},
{"Image Link": "https://images.brickset.com/sets/small/853866-1.jpg?201901050928"},
{"Image Link": "https://images.brickset.com/sets/small/853867-1.jpg?201901170834"},
{"Image Link": "https://images.brickset.com/sets/small/853868-1.jpg?201901270918"},
{"Image Link": "https://images.brickset.com/sets/small/853869-1.jpg?201901270918"},
{"Image Link": "https://images.brickset.com/sets/small/853870-1.jpg?201901270918"},
{"Image Link": "https://images.brickset.com/sets/small/853871-1.jpg?201902101009"},
{"Image Link": "https://images.brickset.com/sets/small/853872-1.jpg?201901270918"},
{"Image Link": "https://images.brickset.com/sets/small/853873-1.jpg?201901270918"},
{"Image Link": "https://images.brickset.com/sets/small/853874-1.jpg?201901270918"},
{"Image Link": "https://images.brickset.com/sets/small/853875-1.jpg?201902200914"},
{"Image Link": "https://images.brickset.com/sets/small/853876-1.jpg?201906150837"},
{"Image Link": "https://images.brickset.com/sets/small/853877-1.jpg?201901170834"},
{"Image Link": "https://images.brickset.com/sets/small/853878-1.jpg?201901170834"},
{"Image Link": "https://images.brickset.com/sets/small/853879-1.jpg?201904040109"},
{"Image Link": "https://images.brickset.com/sets/small/853880-1.jpg?201902101009"},
{"Image Link": "https://images.brickset.com/sets/small/853881-1.jpg?201902101009"},
{"Image Link": "https://images.brickset.com/sets/small/853882-1.jpg?201901050928"},
{"Image Link": "https://images.brickset.com/sets/small/853883-1.jpg?201901050928"},
{"Image Link": "https://images.brickset.com/sets/small/853886-1.jpg?201901170834"},
{"Image Link": "https://images.brickset.com/sets/small/853889-1.jpg?201906150837"},
{"Image Link": "/assets/images/misc/rlfm-white-logo.png"},
{"Image Link": "https://images.brickset.com/sets/small/853890-1.jpg?201909251053"},
{"Image Link": "https://images.brickset.com/sets/small/853891-1.jpg?201906150837"},
{"Image Link": "https://images.brickset.com/sets/small/853892-1.jpg?201906150837"},
{"Image Link": "https://images.brickset.com/sets/small/853893-1.jpg?201901270918"},
{"Image Link": "https://images.brickset.com/sets/small/853894-1.jpg?201901270918"},
{"Image Link": "https://images.brickset.com/sets/small/853899-1.jpg?201901050928"},
{"Image Link": "https://images.brickset.com/sets/small/853900-1.jpg?201902200914"},
{"Image Link": "https://images.brickset.com/sets/small/853901-1.jpg?201906150837"},
{"Image Link": "https://images.brickset.com/sets/small/853902-1.jpg?201902200914"},
{"Image Link": "https://images.brickset.com/sets/small/853903-1.jpg?201903210341"},
{"Image Link": "https://images.brickset.com/sets/small/853904-1.jpg?201903210341"},
{"Image Link": "https://images.brickset.com/sets/small/853905-1.jpg?201903210341"},
{"Image Link": "https://images.brickset.com/sets/small/853906-1.jpg?201902200914"},
{"Image Link": "https://images.brickset.com/sets/small/853907-1.jpg?201909251053"},
{"Image Link": "https://images.brickset.com/sets/small/853908-1.jpg?201908050939"},
{"Image Link": "https://images.brickset.com/sets/small/853910-1.jpg?201902200914"},
{"Image Link": "https://images.brickset.com/sets/small/853911-1.jpg?201907130955"},
{"Image Link": "https://images.brickset.com/sets/small/853912-1.jpg?201904040109"},
{"Image Link": "https://images.brickset.com/sets/small/853913-1.jpg?201902200914"},
{"Image Link": "https://images.brickset.com/sets/small/853914-1.jpg?201903030845"},
{"Image Link": "https://images.brickset.com/sets/small/853915-1.jpg?201902200914"},
{"Image Link": "https://images.brickset.com/sets/small/853917-1.jpg?201908161036"},
{"Image Link": "https://images.brickset.com/sets/small/853918-1.jpg?201901050928"},
{"Image Link": "https://images.brickset.com/sets/small/853919-1.jpg?201906150837"},
{"Image Link": "https://images.brickset.com/sets/small/853920-1.jpg?201905310930"},
{"Image Link": "/assets/images/misc/rlfm-white-logo.png"},
{"Image Link": "https://images.brickset.com/sets/small/853921-1.jpg?201902200914"},
{"Image Link": "https://images.brickset.com/sets/small/853922-1.jpg?201903050956"},
{"Image Link": "https://images.brickset.com/sets/small/853946-1.jpg?201903210341"},
{"Image Link": "https://images.brickset.com/sets/small/853947-1.jpg?201901050928"},
{"Image Link": "https://images.brickset.com/sets/small/853948-1.jpg?201901050928"},
{"Image Link": "https://images.brickset.com/sets/small/853949-1.jpg?201901050928"},
{"Image Link": "https://images.brickset.com/sets/small/853950-1.jpg?201901050928"},
{"Image Link": "https://images.brickset.com/sets/small/853951-1.jpg?201901050928"},
{"Image Link": "https://images.brickset.com/sets/small/853952-1.jpg?201901050928"},
{"Image Link": "https://images.brickset.com/sets/small/853953-1.jpg?201901050928"},
{"Image Link": "https://images.brickset.com/sets/small/853954-1.jpg?201901170834"},
{"Image Link": "https://images.brickset.com/sets/small/853955-1.jpg?201901170834"},
{"Image Link": "https://images.brickset.com/sets/small/853956-1.jpg?201901050928"},
{"Image Link": "https://images.brickset.com/sets/small/853958-1.jpg?201903210341"},
{"Image Link": "https://images.brickset.com/sets/small/853960-1.jpg?201903210341"},
{"Image Link": "https://images.brickset.com/sets/small/853963-1.jpg?201901270918"},
{"Image Link": "https://images.brickset.com/sets/small/853967-1.jpg?201911010819"},
{"Image Link": "https://images.brickset.com/sets/small/853967-2.jpg?202107150135"},
{"Image Link": "https://images.brickset.com/sets/small/853968-1.jpg?201911241006"},
{"Image Link": "https://images.brickset.com/sets/small/853969-1.jpg?201911241006"},
{"Image Link": "https://images.brickset.com/sets/small/853970-1.jpg?201911241006"},
{"Image Link": "https://images.brickset.com/sets/small/854067-1.jpg?201912091206"},
{"Image Link": "https://images.brickset.com/sets/small/NIN891945-1.jpg?201901220859"},
{"Image Link": "https://images.brickset.com/sets/small/NIN891946-1.jpg?201902030900"},
{"Image Link": "https://images.brickset.com/sets/small/891947-1.jpg?201904080346"},
{"Image Link": "/assets/images/misc/rlfm-white-logo.png"},
{"Image Link": "https://images.brickset.com/sets/small/891948-1.jpg?201905260854"},
{"Image Link": "https://images.brickset.com/sets/small/891949-1.jpg?201909190855"},
{"Image Link": "https://images.brickset.com/sets/small/891950-1.jpg?201906110829"},
{"Image Link": "https://images.brickset.com/sets/small/891951-1.jpg?201907130935"},
{"Image Link": "https://images.brickset.com/sets/small/891952-1.jpg?201908051055"},
{"Image Link": "https://images.brickset.com/sets/small/891953-1.jpg?201909190855"},
{"Image Link": "https://images.brickset.com/sets/small/891954-1.jpg?201909190857"},
{"Image Link": "https://images.brickset.com/sets/small/891955-1.jpg?201910030941"},
{"Image Link": "https://images.brickset.com/sets/small/891956-1.jpg?201911070733"},
{"Image Link": "https://images.brickset.com/sets/small/891957-1.jpg?201912030831"},
{"Image Link": "https://images.brickset.com/sets/small/891958-1.jpg?201912310734"},
{"Image Link": "https://images.brickset.com/sets/small/SW911943-1.jpg?201901120846"},
{"Image Link": "https://images.brickset.com/sets/small/911944-1.jpg?201904250832"},
{"Image Link": "https://images.brickset.com/sets/small/SW911945-1.jpg?201903090637"},
{"Image Link": "https://images.brickset.com/sets/small/911946-1.jpg?201904040713"},
{"Image Link": "https://images.brickset.com/sets/small/911947-1.jpg?201905170815"},
{"Image Link": "https://images.brickset.com/sets/small/911948-1.jpg?201906100709"},
{"Image Link": "https://images.brickset.com/sets/small/911949-1.jpg?201907170957"},
{"Image Link": "https://images.brickset.com/sets/small/911950-1.jpg?201908141107"},
{"Image Link": "https://images.brickset.com/sets/small/911951-1.jpg?201909090338"},
{"Image Link": "https://images.brickset.com/sets/small/911952-1.jpg?201910180955"},
{"Image Link": "https://images.brickset.com/sets/small/911953-1.jpg?201910310859"},
{"Image Link": "https://images.brickset.com/sets/small/911954-1.jpg?201912070808"},
{"Image Link": "https://images.brickset.com/sets/small/CITY951901-1.jpg?201902010933"},
{"Image Link": "https://images.brickset.com/sets/small/CITY951902-1.jpg?201903030841"},
{"Image Link": "/assets/images/misc/rlfm-white-logo.png"},
{"Image Link": "https://images.brickset.com/sets/small/CITY951903-1.jpg?201903080636"},
{"Image Link": "https://images.brickset.com/sets/small/951904-1.jpg?201904110823"},
{"Image Link": "https://images.brickset.com/sets/small/951905-1.jpg?201905180819"},
{"Image Link": "https://images.brickset.com/sets/small/951906-1.jpg?201908011042"},
{"Image Link": "https://images.brickset.com/sets/small/951907-1.jpg?201907220857"},
{"Image Link": "https://images.brickset.com/sets/small/951908-1.jpg?201908141106"},
{"Image Link": "https://images.brickset.com/sets/small/951909-1.jpg?201909190858"},
{"Image Link": "https://images.brickset.com/sets/small/951910-1.jpg?201910160849"},
{"Image Link": "https://images.brickset.com/sets/small/951911-1.jpg?201911131136"},
{"Image Link": "https://images.brickset.com/sets/small/951912-1.jpg?201912210748"},
{"Image Link": "https://images.brickset.com/sets/small/2000455-1.jpg?201905170828"},
{"Image Link": "https://images.brickset.com/sets/small/2000456 -1.jpg?201904250835"},
{"Image Link": "https://images.brickset.com/sets/small/3850072-1.jpg?201905260859"},
{"Image Link": "https://images.brickset.com/sets/small/4000034-1.jpg?201906141059"},
{"Image Link": "https://images.brickset.com/sets/small/4000036-1.jpg?201909080305"},
{"Image Link": "https://images.brickset.com/sets/small/4002019-1.jpg?201912040844"},
{"Image Link": "https://images.brickset.com/sets/small/5005471-1.jpg?201912050921"},
{"Image Link": "https://images.brickset.com/sets/small/5005542-1.jpg?201908161036"},
{"Image Link": "https://images.brickset.com/sets/small/5005543-1.jpg?201908161036"},
{"Image Link": "https://images.brickset.com/sets/small/5005578-1.jpg?201908161036"},
{"Image Link": "https://images.brickset.com/sets/small/5005584-1.jpg?202005010755"},
{"Image Link": "https://images.brickset.com/sets/small/5005614-1.jpg?201904230852"},
{"Image Link": "https://images.brickset.com/sets/small/5005618-1.jpg?201908161036"},
{"Image Link": "https://images.brickset.com/sets/small/5005630-1.jpg?201912050921"},
{"Image Link": "https://images.brickset.com/sets/small/5005698-1.jpg?201902101009"},
{"Image Link": "/assets/images/misc/rlfm-white-logo.png"},
{"Image Link": "https://images.brickset.com/sets/small/5005699-1.jpg?201903210341"},
{"Image Link": "https://images.brickset.com/sets/small/5005700-1.jpg?201901170834"},
{"Image Link": "https://images.brickset.com/sets/small/5005701-1.jpg?201901170834"},
{"Image Link": "https://images.brickset.com/sets/small/5005703-1.jpg?201901170834"},
{"Image Link": "https://images.brickset.com/sets/small/5005705-1.jpg?201908161036"},
{"Image Link": "https://images.brickset.com/sets/small/5005706-1.jpg?201908161036"},
{"Image Link": "https://images.brickset.com/sets/small/5005733-1.jpg?201902101009"},
{"Image Link": "https://images.brickset.com/sets/small/5005734-1.jpg?201902101009"},
{"Image Link": "https://images.brickset.com/sets/small/5005735-1.jpg?201902101009"},
{"Image Link": "https://images.brickset.com/sets/small/5005736-1.jpg?201902101009"},
{"Image Link": "https://images.brickset.com/sets/small/5005737-1.jpg?201902101009"},
{"Image Link": "https://images.brickset.com/sets/small/5005738-1.jpg?201902200914"},
{"Image Link": "https://images.brickset.com/sets/small/5005739-1.jpg?201902101009"},
{"Image Link": "https://images.brickset.com/sets/small/5005740-1.jpg?201902101009"},
{"Image Link": "https://images.brickset.com/sets/small/5005741-1.jpg?201902101009"},
{"Image Link": "https://images.brickset.com/sets/small/5005761-1.jpg?201903210341"},
{"Image Link": "https://images.brickset.com/sets/small/5005762-1.jpg?201903210341"},
{"Image Link": "https://images.brickset.com/sets/small/5005763-1.jpg?201903210341"},
{"Image Link": "https://images.brickset.com/sets/small/5005765-1.jpg?201903210341"},
{"Image Link": "https://images.brickset.com/sets/small/5005770-1.jpg?201908050939"},
{"Image Link": "https://images.brickset.com/sets/small/5005775-1.jpg?201901200650"},
{"Image Link": "https://images.brickset.com/sets/small/5005777-1.jpg?201901270918"},
{"Image Link": "https://images.brickset.com/sets/small/5005813-1.jpg?201908050939"},
{"Image Link": "https://images.brickset.com/sets/small/5005818-1.jpg?201904040109"},
{"Image Link": "https://images.brickset.com/sets/small/5005819-1.jpg?201904040109"},
{"Image Link": "/assets/images/misc/rlfm-white-logo.png"},
{"Image Link": "https://images.brickset.com/sets/small/5005820-1.jpg?201904040109"},
{"Image Link": "https://images.brickset.com/sets/small/5005821-1.jpg?201904230850"},
{"Image Link": "https://images.brickset.com/sets/small/5005822-1.jpg?201903210341"},
{"Image Link": "https://images.brickset.com/sets/small/5005823-1.jpg?201905170829"},
{"Image Link": "https://images.brickset.com/sets/small/5005824-1.jpg?201905170829"},
{"Image Link": "https://images.brickset.com/sets/small/5005825-1.jpg?201904230852"},
{"Image Link": "https://images.brickset.com/sets/small/5005834-1.jpg?201908050939"},
{"Image Link": "https://images.brickset.com/sets/small/5005836-1.jpg?201904230852"},
{"Image Link": "https://images.brickset.com/sets/small/5005838-1.jpg?201906150837"},
{"Image Link": "https://images.brickset.com/sets/small/5005842-1.jpg?201904230852"},
{"Image Link": "https://images.brickset.com/sets/small/5005843-1.jpg?201904230852"},
{"Image Link": "https://images.brickset.com/sets/small/5005844-1.jpg?201904230852"},
{"Image Link": "https://images.brickset.com/sets/small/5005846-1.jpg?201904230852"},
{"Image Link": "/assets/images/misc/blankbox.gif"},
{"Image Link": "https://images.brickset.com/sets/small/5005877-1.jpg?201904230852"},
{"Image Link": "https://images.brickset.com/sets/small/5005881-1.jpg?201908050939"},
{"Image Link": "/assets/images/misc/blankbox.gif"},
{"Image Link": "https://images.brickset.com/sets/small/5005883-1.jpg?201912030832"},
{"Image Link": "/assets/images/misc/blankbox.gif"},
{"Image Link": "https://images.brickset.com/sets/small/5005885-1.jpg?201908050939"},
{"Image Link": "/assets/images/misc/blankbox.gif"},
{"Image Link": "/assets/images/misc/blankbox.gif"},
{"Image Link": "https://images.brickset.com/sets/small/5005900-1.jpg?201908050939"},
{"Image Link": "https://images.brickset.com/sets/small/5005901-1.jpg?201908161036"},
{"Image Link": "https://images.brickset.com/sets/small/5005902-1.jpg?201908161036"},
{"Image Link": "/assets/images/misc/rlfm-white-logo.png"},
{"Image Link": "https://images.brickset.com/sets/small/5005903-1.jpg?201908161036"},
{"Image Link": "https://images.brickset.com/sets/small/5005906-1.jpg?201912050921"},
{"Image Link": "https://images.brickset.com/sets/small/5005907-1.jpg?201905310930"},
{"Image Link": "https://images.brickset.com/sets/small/5005910-1.jpg?201908050939"},
{"Image Link": "https://images.brickset.com/sets/small/5005918-1.jpg?201908050939"},
{"Image Link": "https://images.brickset.com/sets/small/5005919-1.jpg?201908050939"},
{"Image Link": "https://images.brickset.com/sets/small/5005920-1.jpg?201908050939"},
{"Image Link": "https://images.brickset.com/sets/small/5005921-1.jpg?201908050939"},
{"Image Link": "https://images.brickset.com/sets/small/5005922-1.jpg?201908050939"},
{"Image Link": "https://images.brickset.com/sets/small/5005923-1.jpg?201908050939"},
{"Image Link": "https://images.brickset.com/sets/small/5005924-1.jpg?201908050939"},
{"Image Link": "https://images.brickset.com/sets/small/5005926-1.jpg?201908050939"},
{"Image Link": "https://images.brickset.com/sets/small/5005927-1.jpg?201908161036"},
{"Image Link": "https://images.brickset.com/sets/small/5005928-1.jpg?201908050939"},
{"Image Link": "https://images.brickset.com/sets/small/5005929-1.jpg?201908050939"},
{"Image Link": "https://images.brickset.com/sets/small/5005933-1.jpg?201912250923"},
{"Image Link": "https://images.brickset.com/sets/small/5005956-1.jpg?201908050939"},
{"Image Link": "https://images.brickset.com/sets/small/5005969-1.jpg?201908050939"},
{"Image Link": "https://images.brickset.com/sets/small/5005996-1.jpg?202102240828"},
{"Image Link": "https://images.brickset.com/sets/small/5005997-1.jpg?201912050921"},
{"Image Link": "https://images.brickset.com/sets/small/5005999-1.jpg?201912050921"},
{"Image Link": "https://images.brickset.com/sets/small/5006003-1.jpg?202103100914"},
{"Image Link": "https://images.brickset.com/sets/small/5006007-1.jpg?201908260410"},
{"Image Link": "https://images.brickset.com/sets/small/5006008-1.jpg?201911131142"},
{"Image Link": "https://images.brickset.com/sets/small/5006016-1.jpg?201908161036"},
{"Image Link": "/assets/images/misc/rlfm-white-logo.png"},
{"Image Link": "https://images.brickset.com/sets/small/5006017-1.jpg?201909150505"},
{"Image Link": "https://images.brickset.com/sets/small/5006027-1.jpg?201911241006"},
{"Image Link": "https://images.brickset.com/sets/small/5006030-1.jpg?201911241006"},
{"Image Link": "/assets/images/misc/blankbox.gif"},
{"Image Link": "/assets/images/misc/blankbox.gif"},
{"Image Link": "/assets/images/misc/blankbox.gif"},
{"Image Link": "/assets/images/misc/blankbox.gif"},
{"Image Link": "https://images.brickset.com/sets/small/5006065-1.jpg?201912050921"},
{"Image Link": "https://images.brickset.com/sets/small/5006066-1.jpg?201911290356"},
{"Image Link": "https://images.brickset.com/sets/small/5006086-1.jpg?202001291110"},
{"Image Link": "https://images.brickset.com/sets/small/6244853-1.jpg?201901220857"},
{"Image Link": "https://images.brickset.com/sets/small/6307985-1.jpg?201909220834"},
{"Image Link": "https://images.brickset.com/sets/small/6307986-1.jpg?201909220834"},
{"Image Link": "https://images.brickset.com/sets/small/6307995-1.jpg?201909220834"},
{"Image Link": "https://images.brickset.com/sets/small/6307997-1.jpg?201909220834"},
{"Image Link": "/assets/images/misc/blankbox.gif"},
{"Image Link": "/assets/images/misc/blankbox.gif"},
{"Image Link": "/assets/images/misc/blankbox.gif"},
{"Image Link": "/assets/images/misc/blankbox.gif"},
{"Image Link": "https://images.brickset.com/sets/small/6313092-1.jpg?201912010704"},
{"Image Link": "https://images.brickset.com/sets/small/5006085-1.jpg?202011280913"},
{"Image Link": "https://images.brickset.com/sets/small/5006085-1.jpg?201911200934"},
{"Image Link": "https://images.brickset.com/sets/small/6315023-1.jpg?201911290351"},
{"Image Link": "https://images.brickset.com/sets/small/AMSTERDAM-1.jpg?201912050353"},
{"Image Link": "https://images.brickset.com/sets/small/100STORES-1.jpg?201901061007"},
{"Image Link": "/assets/images/misc/rlfm-white-logo.png"},
{"Image Link": "https://images.brickset.com/sets/small/ARENDELLE-1.jpg?201912091208"},
{"Image Link": "https://images.brickset.com/sets/small/BEIJING-1.jpg?201903061015"},
{"Image Link": "https://images.brickset.com/sets/small/BEIJING-2.jpg?201906110829"},
{"Image Link": "https://images.brickset.com/sets/small/BL19001-1.jpg?201904110106"},
{"Image Link": "https://images.brickset.com/sets/small/BL19002-1.jpg?201904110106"},
{"Image Link": "https://images.brickset.com/sets/small/BL19003-1.jpg?201904110106"},
{"Image Link": "https://images.brickset.com/sets/small/BL19004-1.jpg?201904110107"},
{"Image Link": "https://images.brickset.com/sets/small/BL19005-1.jpg?201904110107"},
{"Image Link": "https://images.brickset.com/sets/small/BL19006-1.jpg?201904110107"},
{"Image Link": "https://images.brickset.com/sets/small/BL19007-1.jpg?201904110107"},
{"Image Link": "https://images.brickset.com/sets/small/BL19008-1.jpg?201904110107"},
{"Image Link": "https://images.brickset.com/sets/small/BL19009-1.jpg?201904110107"},
{"Image Link": "https://images.brickset.com/sets/small/BL19010-1.jpg?201904110108"},
{"Image Link": "https://images.brickset.com/sets/small/BL19011-1.jpg?201904110108"},
{"Image Link": "https://images.brickset.com/sets/small/BL19012-1.jpg?201904110108"},
{"Image Link": "https://images.brickset.com/sets/small/BL19013-1.jpg?201904110108"},
{"Image Link": "https://images.brickset.com/sets/small/Blocks052-1.jpg?202004020631"},
{"Image Link": "https://images.brickset.com/sets/small/Blocks053-1.jpg?202004020631"},
{"Image Link": "https://images.brickset.com/sets/small/Blocks054-1.jpg?202004020631"},
{"Image Link": "https://images.brickset.com/sets/small/Blocks055-1.jpg?202004020631"},
{"Image Link": "https://images.brickset.com/sets/small/Blocks056-1.jpg?202004020631"},
{"Image Link": "https://images.brickset.com/sets/small/Blocks057-1.jpg?202004020631"},
{"Image Link": "https://images.brickset.com/sets/small/Blocks058-1.jpg?202004020631"},
{"Image Link": "https://images.brickset.com/sets/small/Blocks059-1.jpg?202004020631"},
{"Image Link": "https://images.brickset.com/sets/small/Blocks060-1.jpg?202004020631"},
{"Image Link": "/assets/images/misc/rlfm-white-logo.png"},
{"Image Link": "https://images.brickset.com/sets/small/Blocks061-1.jpg?202004020631"},
{"Image Link": "https://images.brickset.com/sets/small/Blocks062-1.jpg?202004020631"},
{"Image Link": "https://images.brickset.com/sets/small/BLOCKS063-1.jpg?202005100635"},
{"Image Link": "https://images.brickset.com/sets/small/BRICKFANATICS003-1.jpg?202004031156"},
{"Image Link": "https://images.brickset.com/sets/small/BRICKFANATICS004-1.jpg?202004031156"},
{"Image Link": "https://images.brickset.com/sets/small/BRICKFANATICS005-1.jpg?202004031156"},
{"Image Link": "https://images.brickset.com/sets/small/BRICKFANATICS006-1.jpg?202004031156"},
{"Image Link": "https://images.brickset.com/sets/small/BRICKFANATICS007-1.jpg?202004031157"},
{"Image Link": "https://images.brickset.com/sets/small/BRICKFANATICS008-1.jpg?202004031157"},
{"Image Link": "https://images.brickset.com/sets/small/BRICKFANATICS009-1.jpg?202004031159"},
{"Image Link": "https://images.brickset.com/sets/small/BRICKFANATICS010-1.jpg?202004031159"},
{"Image Link": "https://images.brickset.com/sets/small/BRICKFANATICS011-1.jpg?202004031159"},
{"Image Link": "https://images.brickset.com/sets/small/BRICKFANATICS012-1.jpg?202004031159"},
{"Image Link": "https://images.brickset.com/sets/small/BRICKJOURNAL055-1.jpg?202011241133"},
{"Image Link": "https://images.brickset.com/sets/small/BRICKJOURNAL056-1.jpg?202011241134"},
{"Image Link": "https://images.brickset.com/sets/small/BRICKJOURNAL057-1.jpg?202011241135"},
{"Image Link": "https://images.brickset.com/sets/small/BRICKJOURNAL058-1.jpg?202011241136"},
{"Image Link": "https://images.brickset.com/sets/small/BRICKJOURNAL059-1.jpg?202011241138"},
{"Image Link": "https://images.brickset.com/sets/small/BRICKJOURNAL060-1.jpg?202011241139"},
{"Image Link": "https://images.brickset.com/sets/small/CAPTAINMARVEL-1.jpg?202101201119"},
{"Image Link": "https://images.brickset.com/sets/small/COLOGNE-1.jpg?201907130939"},
{"Image Link": "https://images.brickset.com/sets/small/COOLCAR-1.jpg?201908030715"},
{"Image Link": "https://images.brickset.com/sets/small/EASTERCHICK-1.jpg?201904250837"},
{"Image Link": "https://images.brickset.com/sets/small/ELEPHANT-1.jpg?201904250838"},
{"Image Link": "https://images.brickset.com/sets/small/EMMETHOUSE-1.jpg?201903061021"},
{"Image Link": "/assets/images/misc/rlfm-white-logo.png"},
{"Image Link": "https://images.brickset.com/sets/small/FLOWER-1.jpg?201904250839"},
{"Image Link": "https://images.brickset.com/sets/small/GANYMEDE-1.jpg?201902090838"},
{"Image Link": "https://images.brickset.com/sets/small/HARLEY-1.jpg?201908011043"},
{"Image Link": "https://images.brickset.com/sets/small/ISBN0241357527-1.jpg?201807160808"},
{"Image Link": "https://images.brickset.com/sets/small/ISBN0241357594-1.jpg?201908050953"},
{"Image Link": "https://images.brickset.com/sets/small/ISBN0241363500-1.jpg?201901270900"},
{"Image Link": "https://images.brickset.com/sets/small/ISBN024136373X-1.jpg?201908051003"},
{"Image Link": "https://images.brickset.com/sets/small/ISBN0241363764-1.jpg?201909091156"},
{"Image Link": "https://images.brickset.com/sets/small/ISBN0241381711-1.jpg?201901270901"},
{"Image Link": "https://images.brickset.com/sets/small/ISBN9780241395431-1.jpg?202011050309"},
{"Image Link": "https://images.brickset.com/sets/small/ISBN0241397359-1.jpg?201909091200"},
{"Image Link": "https://images.brickset.com/sets/small/ISBN0241412099-1.jpg?201910211153"},
{"Image Link": "https://images.brickset.com/sets/small/ISBN048683235X-1.jpg?201901270904"},
{"Image Link": "https://images.brickset.com/sets/small/ISBN1070422126-1.jpg?201908051002"},
{"Image Link": "https://images.brickset.com/sets/small/ISBN1080207961-1.jpg?201908051002"},
{"Image Link": "https://images.brickset.com/sets/small/ISBN1081986611-1.jpg?201908051002"},
{"Image Link": "https://images.brickset.com/sets/small/ISBN1091708533-1.jpg?201908051002"},
{"Image Link": "https://images.brickset.com/sets/small/ISBN1092282297-1.jpg?201905170727"},
{"Image Link": "https://images.brickset.com/sets/small/ISBN1419734687-1.jpg?201901270901"},
{"Image Link": "https://images.brickset.com/sets/small/ISBN1465485767-1.jpg?201901270901"},
{"Image Link": "https://images.brickset.com/sets/small/ISBN1513262114-1.jpg?201908051003"},
{"Image Link": "https://images.brickset.com/sets/small/ISBN1513262122-1.jpg?201901270902"},
{"Image Link": "https://images.brickset.com/sets/small/ISBN1593279604-1.jpg?201901270902"},
{"Image Link": "https://images.brickset.com/sets/small/ISBN1624149103-1.jpg?202005110403"},
{"Image Link": "https://images.brickset.com/sets/small/ISBN1718500165-1.jpg?201908050955"},
{"Image Link": "/assets/images/misc/rlfm-white-logo.png"},
{"Image Link": "https://images.brickset.com/sets/small/KNIGHTBUS-1.jpg?201910020904"},
{"Image Link": "https://images.brickset.com/sets/small/LUKE-1.jpg?202007140112"},
{"Image Link": "https://images.brickset.com/sets/small/OLAF-1.jpg?201911270733"},
{"Image Link": "https://images.brickset.com/sets/small/PANDA-1.jpg?201904110844"},
{"Image Link": "https://images.brickset.com/sets/small/PIG-1.jpg?201904110825"},
{"Image Link": "https://images.brickset.com/sets/small/REDSOX2019-1.jpg?201907130936"},
{"Image Link": "https://images.brickset.com/sets/small/SDCC2019-3.jpg?201907110309"},
{"Image Link": "https://images.brickset.com/sets/small/SDCC2019-1.jpg?201906290507"},
{"Image Link": "https://images.brickset.com/sets/small/SDCC2019-2.jpg?201907080507"},
{"Image Link": "https://images.brickset.com/sets/small/SNITCH-1.jpg?201908011044"},
{"Image Link": "https://images.brickset.com/sets/small/ST-1.jpg?201905151137"},
{"Image Link": "https://images.brickset.com/sets/small/STORMBREAKER-1.jpg?201905170842"},
{"Image Link": "https://images.brickset.com/sets/small/TANTIVEIV-1.jpg?201905170840"},
{"Image Link": "/assets/images/misc/blankbox.gif"},
{"Image Link": "https://images.brickset.com/sets/small/XWING-1.jpg?201905260906"},
{"Image Link": "https://images.brickset.com/sets/small/XWING-2.jpg?202004201042"},
{"Image Link": "/assets/images/misc/rlfm-white-logo.png"}
]